[{"id":1,"sort_id":1,"scenario_image_id":1,"prologue_id":80000001,"turn_set_id":1,"hint_rate":0,"start_date":1577804400,"end_date":2524575600,"additional_icon_set_id":0,"bg_id":5,"bg_sub_id":5110,"bg_offset_x":375,"sec_bg_id":37,"sec_bg_sub_id":110,"label_font_color":"FFFFFF","label_bg_color":"9CD127","chara_program_change_flag":0,"max_speed":200,"max_stamina":200,"max_pow":200,"max_guts":200,"max_wiz":200,"gimmick_discount_rate":5000},{"id":2,"sort_id":2,"scenario_image_id":2,"prologue_id":80000002,"turn_set_id":2,"hint_rate":0,"start_date":1630292400,"end_date":2524575600,"additional_icon_set_id":0,"bg_id":124,"bg_sub_id":2111,"bg_offset_x":0,"sec_bg_id":79,"sec_bg_sub_id":110,"label_font_color":"FFFFFF","label_bg_color":"18B1FF","chara_program_change_flag":0,"max_speed":100,"max_stamina":100,"max_pow":100,"max_guts":100,"max_wiz":600,"gimmick_discount_rate":5000},{"id":3,"sort_id":4,"scenario_image_id":3,"prologue_id":80000003,"turn_set_id":3,"hint_rate":0,"start_date":1661310000,"end_date":2524575600,"additional_icon_set_id":0,"bg_id":120,"bg_sub_id":132,"bg_offset_x":0,"sec_bg_id":133,"sec_bg_sub_id":110,"label_font_color":"FFFFFF","label_bg_color":"B08FFF","chara_program_change_flag":0,"max_speed":400,"max_stamina":100,"max_pow":100,"max_guts":300,"max_wiz":100,"gimmick_discount_rate":5000},{"id":4,"sort_id":3,"scenario_image_id":4,"prologue_id":80000004,"turn_set_id":4,"hint_rate":0,"start_date":1645671600,"end_date":2524575600,"additional_icon_set_id":0,"bg_id":24,"bg_sub_id":110,"bg_offset_x":0,"sec_bg_id":56,"sec_bg_sub_id":111,"label_font_color":"FFFFFF","label_bg_color":"EABA00","chara_program_change_flag":1,"max_speed":0,"max_stamina":700,"max_pow":0,"max_guts":0,"max_wiz":300,"gimmick_discount_rate":5000},{"id":5,"sort_id":5,"scenario_image_id":5,"prologue_id":80000005,"turn_set_id":5,"hint_rate":0,"start_date":1677207600,"end_date":2524575600,"additional_icon_set_id":5,"bg_id":50,"bg_sub_id":0,"bg_offset_x":0,"sec_bg_id":50,"sec_bg_sub_id":0,"label_font_color":"FFFFFF","label_bg_color":"fb5f5f","chara_program_change_flag":0,"max_speed":300,"max_stamina":200,"max_pow":300,"max_guts":100,"max_wiz":100,"gimmick_discount_rate":5000},{"id":6,"sort_id":6,"scenario_image_id":6,"prologue_id":80000006,"turn_set_id":6,"hint_rate":0,"start_date":1692846000,"end_date":2524575600,"additional_icon_set_id":0,"bg_id":243,"bg_sub_id":2110,"bg_offset_x":0,"sec_bg_id":243,"sec_bg_sub_id":2111,"label_font_color":"FFFFFF","label_bg_color":"4B84F4","chara_program_change_flag":1,"max_speed":400,"max_stamina":400,"max_pow":300,"max_guts":300,"max_wiz":100,"gimmick_discount_rate":5000}]