[{"path":"sound\\v\\snd_voi_teamst_st_106900_1004.awb","codec":"CRI HCA","metadataFormat":"CRI HCA header","channels":1,"channelMask":4,"layout":"flat","sampleRate":48000,"bitRate":131000,"samples":44229,"durationMs":921,"looping":false,"loopStartSample":null,"loopEndSample":null,"loopStartTimeMs":null,"loopEndTimeMs":null,"streamName":"snd_voi_teamst_st_106900_1004_00"},{"path":"sound\\v\\snd_voi_teamst_st_106900_1004.awb","codec":"CRI HCA","metadataFormat":"CRI HCA header","channels":1,"channelMask":4,"layout":"flat","sampleRate":48000,"bitRate":130000,"samples":53356,"durationMs":1112,"looping":false,"loopStartSample":null,"loopEndSample":null,"loopStartTimeMs":null,"loopEndTimeMs":null,"streamName":"snd_voi_teamst_st_106900_1004_01"}]