[{"path":"sound\\v\\snd_voi_roulette_102300.awb","codec":"CRI HCA","metadataFormat":"CRI HCA header","channels":1,"channelMask":4,"layout":"flat","sampleRate":48000,"bitRate":134000,"samples":23690,"durationMs":494,"looping":false,"loopStartSample":null,"loopEndSample":null,"loopStartTimeMs":null,"loopEndTimeMs":null,"streamName":"snd_voi_roulette_102300_0000"},{"path":"sound\\v\\snd_voi_roulette_102300.awb","codec":"CRI HCA","metadataFormat":"CRI HCA header","channels":1,"channelMask":4,"layout":"flat","sampleRate":48000,"bitRate":130000,"samples":42599,"durationMs":887,"looping":false,"loopStartSample":null,"loopEndSample":null,"loopStartTimeMs":null,"loopEndTimeMs":null,"streamName":"snd_voi_roulette_102300_0001"},{"path":"sound\\v\\snd_voi_roulette_102300.awb","codec":"CRI HCA","metadataFormat":"CRI HCA header","channels":1,"channelMask":4,"layout":"flat","sampleRate":48000,"bitRate":132000,"samples":26932,"durationMs":561,"looping":false,"loopStartSample":null,"loopEndSample":null,"loopStartTimeMs":null,"loopEndTimeMs":null,"streamName":"snd_voi_roulette_102300_0002"},{"path":"sound\\v\\snd_voi_roulette_102300.awb","codec":"CRI HCA","metadataFormat":"CRI HCA header","channels":1,"channelMask":4,"layout":"flat","sampleRate":48000,"bitRate":130000,"samples":39440,"durationMs":822,"looping":false,"loopStartSample":null,"loopEndSample":null,"loopStartTimeMs":null,"loopEndTimeMs":null,"streamName":"snd_voi_roulette_102300_0003"},{"path":"sound\\v\\snd_voi_roulette_102300.awb","codec":"CRI HCA","metadataFormat":"CRI HCA header","channels":1,"channelMask":4,"layout":"flat","sampleRate":48000,"bitRate":129000,"samples":89095,"durationMs":1856,"looping":false,"loopStartSample":null,"loopEndSample":null,"loopStartTimeMs":null,"loopEndTimeMs":null,"streamName":"snd_voi_roulette_102300_0004"}]