[{"path":"sound\\v\\snd_voi_outgame_106101.awb","codec":"CRI HCA","metadataFormat":"CRI HCA header","channels":1,"channelMask":4,"layout":"flat","sampleRate":48000,"bitRate":128000,"samples":167291,"durationMs":3485,"looping":false,"loopStartSample":null,"loopEndSample":null,"loopStartTimeMs":null,"loopEndTimeMs":null,"streamName":"snd_voi_outgame_106101_0000"},{"path":"sound\\v\\snd_voi_outgame_106101.awb","codec":"CRI HCA","metadataFormat":"CRI HCA header","channels":1,"channelMask":4,"layout":"flat","sampleRate":48000,"bitRate":128000,"samples":200258,"durationMs":4172,"looping":false,"loopStartSample":null,"loopEndSample":null,"loopStartTimeMs":null,"loopEndTimeMs":null,"streamName":"snd_voi_outgame_106101_0001"},{"path":"sound\\v\\snd_voi_outgame_106101.awb","codec":"CRI HCA","metadataFormat":"CRI HCA header","channels":1,"channelMask":4,"layout":"flat","sampleRate":48000,"bitRate":128000,"samples":124221,"durationMs":2588,"looping":false,"loopStartSample":null,"loopEndSample":null,"loopStartTimeMs":null,"loopEndTimeMs":null,"streamName":"snd_voi_outgame_106101_0003"}]