[{"path":"sound\\v\\snd_voi_training_104502.awb","codec":"CRI HCA","metadataFormat":"CRI HCA header","channels":1,"channelMask":4,"layout":"flat","sampleRate":48000,"bitRate":128000,"samples":354333,"durationMs":7382,"looping":false,"loopStartSample":null,"loopEndSample":null,"loopStartTimeMs":null,"loopEndTimeMs":null,"streamName":"snd_voi_training_104502_0000"},{"path":"sound\\v\\snd_voi_training_104502.awb","codec":"CRI HCA","metadataFormat":"CRI HCA header","channels":1,"channelMask":4,"layout":"flat","sampleRate":48000,"bitRate":128000,"samples":427140,"durationMs":8899,"looping":false,"loopStartSample":null,"loopEndSample":null,"loopStartTimeMs":null,"loopEndTimeMs":null,"streamName":"snd_voi_training_104502_0001"},{"path":"sound\\v\\snd_voi_training_104502.awb","codec":"CRI HCA","metadataFormat":"CRI HCA header","channels":1,"channelMask":4,"layout":"flat","sampleRate":48000,"bitRate":128000,"samples":446487,"durationMs":9302,"looping":false,"loopStartSample":null,"loopEndSample":null,"loopStartTimeMs":null,"loopEndTimeMs":null,"streamName":"snd_voi_training_104502_0002"},{"path":"sound\\v\\snd_voi_training_104502.awb","codec":"CRI HCA","metadataFormat":"CRI HCA header","channels":1,"channelMask":4,"layout":"flat","sampleRate":48000,"bitRate":128000,"samples":437623,"durationMs":9117,"looping":false,"loopStartSample":null,"loopEndSample":null,"loopStartTimeMs":null,"loopEndTimeMs":null,"streamName":"snd_voi_training_104502_0003"},{"path":"sound\\v\\snd_voi_training_104502.awb","codec":"CRI HCA","metadataFormat":"CRI HCA header","channels":1,"channelMask":4,"layout":"flat","sampleRate":48000,"bitRate":128000,"samples":425247,"durationMs":8859,"looping":false,"loopStartSample":null,"loopEndSample":null,"loopStartTimeMs":null,"loopEndTimeMs":null,"streamName":"snd_voi_training_104502_0005"},{"path":"sound\\v\\snd_voi_training_104502.awb","codec":"CRI HCA","metadataFormat":"CRI HCA header","channels":1,"channelMask":4,"layout":"flat","sampleRate":48000,"bitRate":128000,"samples":393850,"durationMs":8205,"looping":false,"loopStartSample":null,"loopEndSample":null,"loopStartTimeMs":null,"loopEndTimeMs":null,"streamName":"snd_voi_training_104502_0006"},{"path":"sound\\v\\snd_voi_training_104502.awb","codec":"CRI HCA","metadataFormat":"CRI HCA header","channels":1,"channelMask":4,"layout":"flat","sampleRate":48000,"bitRate":128000,"samples":451843,"durationMs":9413,"looping":false,"loopStartSample":null,"loopEndSample":null,"loopStartTimeMs":null,"loopEndTimeMs":null,"streamName":"snd_voi_training_104502_0007"},{"path":"sound\\v\\snd_voi_training_104502.awb","codec":"CRI HCA","metadataFormat":"CRI HCA header","channels":1,"channelMask":4,"layout":"flat","sampleRate":48000,"bitRate":128000,"samples":202447,"durationMs":4218,"looping":false,"loopStartSample":null,"loopEndSample":null,"loopStartTimeMs":null,"loopEndTimeMs":null,"streamName":"snd_voi_training_104502_0008"},{"path":"sound\\v\\snd_voi_training_104502.awb","codec":"CRI HCA","metadataFormat":"CRI HCA header","channels":1,"channelMask":4,"layout":"flat","sampleRate":48000,"bitRate":128000,"samples":146943,"durationMs":3061,"looping":false,"loopStartSample":null,"loopEndSample":null,"loopStartTimeMs":null,"loopEndTimeMs":null,"streamName":"snd_voi_training_104502_0009"}]