[{"path":"sound\\v\\snd_voi_teamst_st_103700_1046.awb","codec":"CRI HCA","metadataFormat":"CRI HCA header","channels":1,"channelMask":4,"layout":"flat","sampleRate":48000,"bitRate":129000,"samples":43762,"durationMs":912,"looping":false,"loopStartSample":null,"loopEndSample":null,"loopStartTimeMs":null,"loopEndTimeMs":null,"streamName":"snd_voi_teamst_st_103700_1046_00"},{"path":"sound\\v\\snd_voi_teamst_st_103700_1046.awb","codec":"CRI HCA","metadataFormat":"CRI HCA header","channels":1,"channelMask":4,"layout":"flat","sampleRate":48000,"bitRate":128000,"samples":79719,"durationMs":1661,"looping":false,"loopStartSample":null,"loopEndSample":null,"loopStartTimeMs":null,"loopEndTimeMs":null,"streamName":"snd_voi_teamst_st_103700_1046_01"}]